mytelegrambotlib/__init__.py
mytelegrambotlib/my_telegram_bot.py
mytelegrambotlib-0.1.3.dist-info/LICENSE
mytelegrambotlib-0.1.3.dist-info/METADATA
mytelegrambotlib-0.1.3.dist-info/WHEEL
mytelegrambotlib-0.1.3.dist-info/top_level.txt
mytelegrambotlib-0.1.3.dist-info/RECORD
