Metadata-Version: 2.1
Name: mytelegrambotlib
Version: 0.1.3
Summary: Library with telegram bot for homework
Home-page: UNKNOWN
Author: Leonid Dubrovin
License: UNKNOWN
Platform: UNKNOWN
License-File: LICENSE
Requires-Dist: requests
